a_pandas_ex_split_on_common_char/README.MD
a_pandas_ex_split_on_common_char/__init__.py
a_pandas_ex_split_on_common_char/requirements.txt
a_pandas_ex_split_on_common_char/thirdparty.json
a_pandas_ex_split_on_common_char-0.10.dist-info/LICENSE.rst
a_pandas_ex_split_on_common_char-0.10.dist-info/METADATA
a_pandas_ex_split_on_common_char-0.10.dist-info/WHEEL
a_pandas_ex_split_on_common_char-0.10.dist-info/top_level.txt
a_pandas_ex_split_on_common_char-0.10.dist-info/RECORD
