Metadata-Version: 2.1
Name: a-pandas-ex-split-on-common-char
Version: 0.10
Summary: Splits the elements in a Series using a common separator character and returns a DataFrame
Home-page: https://github.com/hansalemaos/a_pandas_ex_split_on_common_char
Author: Johannes Fischer
Author-email: aulasparticularesdealemaosp@gmail.com
License: MIT
Keywords: split,pandas,columns
Classifier: Development Status :: 4 - Beta
Classifier: Programming Language :: Python :: 3 :: Only
Classifier: Programming Language :: Python :: 3.10
Classifier: Topic :: Software Development :: Libraries :: Python Modules
Classifier: Topic :: Utilities
License-File: LICENSE.rst
Requires-Dist: numexpr
Requires-Dist: numpy
Requires-Dist: pandas
